MANIFEST.in
README.rst
TODO.rst
requirements.txt
setup.py
pip_create/__init__.py
pip_create/_version.py
pip_create.egg-info/PKG-INFO
pip_create.egg-info/SOURCES.txt
pip_create.egg-info/dependency_links.txt
pip_create.egg-info/entry_points.txt
pip_create.egg-info/requires.txt
pip_create.egg-info/top_level.txt
pip_create/questions/__init__.py
pip_create/questions/choice.py
pip_create/questions/default.py
pip_create/questions/question.py
pip_create/templates/base.j2
pip_create/templates/long_description.j2
pip_create/templates/packages.j2
pip_create/templates/requirements.j2
pip_create/templates/setup.j2
pip_create/util/__init__.py