Metadata-Version: 1.1
Name: pip-create
Version: 0.3.1
Summary: Tools to create a Python distribution for use with pip
Home-page: https://github.com/jackmaney/pip-create
Author: Jack Maney
Author-email: jackmaney@gmail.com
License: MIT
Platform: UNKNOWN
Classifier: Programming Language :: Python :: 2.7
